{
  "orders": [
    {
      "buyerName": "David",
      "products": [
        {
          "name": "Crema hidratante",
          "description": "Crema para uso de cara y cuerpo",
          "price": 70000.0,
          "quantityAvailable": 39,
          "category": "BEAUTY_AND_PERSONAL_CARE",
          "timesPurchased": 1
        },
        {
          "name": "Libro de aventuras",
          "description": "Libro de aventuras para todas las edades",
          "price": 30000.0,
          "quantityAvailable": 98,
          "category": "BOOKS",
          "timesPurchased": 2
        }
      ],
      "totalPrice": 0.0,
      "date": "May 7, 2023 11:21:15 PM"
    },
    {
      "buyerName": "Juan",
      "products": [
        {
          "name": "Cartulina",
          "description": "Pliego de cartulina color azul",
          "price": 1200.0,
          "quantityAvailable": 49,
          "category": "STATIONERY",
          "timesPurchased": 1
        },
        {
          "name": "Bombillo",
          "description": "Bombillo de luz calida",
          "price": 60000.0,
          "quantityAvailable": 29,
          "category": "ELECTRONICS",
          "timesPurchased": 1
        }
      ],
      "totalPrice": 0.0,
      "date": "May 7, 2023 11:20:32 PM"
    },
    {
      "buyerName": "Maria",
      "products": [
        {
          "name": "Bicicleta",
          "description": "Bicicleta apta para largas rutas",
          "price": 150000.0,
          "quantityAvailable": 15,
          "category": "SPORTS",
          "timesPurchased": 5
        }
      ],
      "totalPrice": 150000.0,
      "date": "May 7, 2023 11:21:41 PM"
    },
    {
      "buyerName": "Sara",
      "products": [
        {
          "name": "Libro de aventuras",
          "description": "Libro de aventuras para todas las edades",
          "price": 30000.0,
          "quantityAvailable": 98,
          "category": "BOOKS",
          "timesPurchased": 2
        },
        {
          "name": "Bicicleta",
          "description": "Bicicleta apta para largas rutas",
          "price": 150000.0,
          "quantityAvailable": 15,
          "category": "SPORTS",
          "timesPurchased": 5
        }
      ],
      "totalPrice": 0.0,
      "date": "May 7, 2023 11:20:49 PM"
    }
  ],
  "products": [
    {
      "name": "Bicicleta",
      "description": "Bicicleta apta para largas rutas",
      "price": 150000.0,
      "quantityAvailable": 15,
      "category": "SPORTS",
      "timesPurchased": 5
    },
    {
      "name": "Bombillo",
      "description": "Bombillo de luz calida",
      "price": 60000.0,
      "quantityAvailable": 29,
      "category": "ELECTRONICS",
      "timesPurchased": 1
    },
    {
      "name": "Cartulina",
      "description": "Pliego de cartulina color azul",
      "price": 1200.0,
      "quantityAvailable": 49,
      "category": "STATIONERY",
      "timesPurchased": 1
    },
    {
      "name": "Crema hidratante",
      "description": "Crema para uso de cara y cuerpo",
      "price": 70000.0,
      "quantityAvailable": 39,
      "category": "BEAUTY_AND_PERSONAL_CARE",
      "timesPurchased": 1
    },
    {
      "name": "Libro de aventuras",
      "description": "Libro de aventuras para todas las edades",
      "price": 30000.0,
      "quantityAvailable": 98,
      "category": "BOOKS",
      "timesPurchased": 2
    },
    {
      "name": "Bicicleta",
      "description": "Bicicleta apta para largas rutas",
      "price": 150000.0,
      "quantityAvailable": 15,
      "category": "SPORTS",
      "timesPurchased": 5
    }
  ]
}